{
  "pages": [
    "Home",
    "Product Details",
    "Cart"
  ],
  "navigation": [
    {
      "name": "PRODUCT STORE",
      "destination": "Home"
    },
    {
      "name": "Home",
      "destination": "Home"
    },
    {
      "name": "Contact",
      "destination": "Contact Modal"
    },
    {
      "name": "About us",
      "destination": "About Us Video Modal"
    },
    {
      "name": "Cart",
      "destination": "Cart"
    },
    {
      "name": "Log in",
      "destination": "Log In Modal"
    },
    {
      "name": "Log out",
      "destination": "Home (User Logout)"
    },
    {
      "name": "Sign up",
      "destination": "Sign Up Modal"
    },
    {
      "name": "Phones",
      "destination": "Home (Category Filter)"
    },
    {
      "name": "Laptops",
      "destination": "Home (Category Filter)"
    },
    {
      "name": "Monitors",
      "destination": "Home (Category Filter)"
    },
    {
      "name": "Product Link",
      "destination": "Product Details"
    },
    {
      "name": "Pagination Previous",
      "destination": "Home (Product List)"
    },
    {
      "name": "Pagination Next",
      "destination": "Home (Product List)"
    }
  ],
  "forms": [
    {
      "name": "Contact Form",
      "fields": [
        "Contact Email",
        "Contact Name",
        "Message"
      ],
      "destination": "Home (Contact Modal)"
    },
    {
      "name": "Sign Up Form",
      "fields": [
        "Username",
        "Password"
      ],
      "destination": "Home (Sign Up Modal)"
    },
    {
      "name": "Log In Form",
      "fields": [
        "Username",
        "Password"
      ],
      "destination": "Home (Log In Modal)"
    },
    {
      "name": "Product Pagination",
      "fields": [],
      "destination": "Home (Product List)"
    }
  ],
  "userFlows": [
    "Browse Products & Categories",
    "View Product Details",
    "User Registration",
    "User Authentication (Login/Logout)",
    "Contact Support",
    "View About Us Information",
    "Access Cart"
  ],
  "testIdeas": [
    {
      "id": "HOME-001",
      "title": "Verify product categories filter products correctly",
      "page": "Home",
      "priority": "Medium",
      "type": "Positive",
      "reason": "Core functionality to explore products effectively."
    },
    {
      "id": "HOME-002",
      "title": "Verify product pagination navigates correctly",
      "page": "Home",
      "priority": "Medium",
      "type": "Positive",
      "reason": "Essential for viewing all products listed on the home page."
    },
    {
      "id": "PROD-001",
      "title": "Verify product details page loads with correct information",
      "page": "Product Details",
      "priority": "Medium",
      "type": "Positive",
      "reason": "Fundamental user journey to inspect products before purchase."
    },
    {
      "id": "SIGNUP-001",
      "title": "Verify successful user registration",
      "page": "Sign Up",
      "priority": "High",
      "type": "Smoke",
      "reason": "Authentication is a critical business flow."
    },
    {
      "id": "SIGNUP-002",
      "title": "Verify registration with existing username fails",
      "page": "Sign Up",
      "priority": "High",
      "type": "Negative",
      "reason": "Prevent creation of duplicate user accounts."
    },
    {
      "id": "LOGIN-001",
      "title": "Verify successful user login",
      "page": "Login",
      "priority": "High",
      "type": "Smoke",
      "reason": "Authentication is a critical business flow."
    },
    {
      "id": "LOGIN-002",
      "title": "Verify login with invalid credentials fails",
      "page": "Login",
      "priority": "High",
      "type": "Negative",
      "reason": "Ensures security and correct error handling for authentication."
    },
    {
      "id": "LOGOUT-001",
      "title": "Verify successful user logout",
      "page": "Home",
      "priority": "High",
      "type": "Smoke",
      "reason": "Essential for managing user sessions and security."
    },
    {
      "id": "CONTACT-001",
      "title": "Verify sending a contact message successfully",
      "page": "Home (Contact Modal)",
      "priority": "Low",
      "type": "Positive",
      "reason": "Important for user communication and support."
    },
    {
      "id": "CONTACT-002",
      "title": "Verify contact form displays validation errors for empty fields",
      "page": "Home (Contact Modal)",
      "priority": "Low",
      "type": "Negative",
      "reason": "Ensures proper form validation and user feedback."
    },
    {
      "id": "ABOUTUS-001",
      "title": "Verify 'About us' video modal opens and video plays",
      "page": "Home (About Us Video Modal)",
      "priority": "Low",
      "type": "Positive",
      "reason": "Informational content should be accessible and functional."
    },
    {
      "id": "CART-001",
      "title": "Verify navigation to the Cart page",
      "page": "Cart",
      "priority": "High",
      "type": "Regression",
      "reason": "Shopping cart is a core business flow."
    }
  ],
  "risks": [
    "Product images lack meaningful alt text, impacting accessibility for screen reader users.",
    "Product prices are rendered as H5 headings, which is semantically incorrect and affects document outline.",
    "The 'About us' video player's accessibility (e.g., keyboard navigation, ARIA labels for controls) needs thorough verification.",
    "Generic error label elements for forms (#errors, #errorl) may not provide specific or contextual error messages to users.",
    "Product descriptions are truncated with 'text-overflow: ellipsis' without an clear option to view full text, affecting usability.",
    "Modal dialogs (Contact, Sign Up, Log In, About Us) need full accessibility checks for keyboard trapping and focus management.",
    "Color contrast of text elements, especially within navigation and footer, should be verified to meet WCAG standards."
  ]
}